alpaca/__init__.py
alpaca/configuration.py
alpaca/logging.py
alpaca/main.py
alpaca/package.py
alpaca/package_description.py
alpaca/package_manager.py
alpaca/repository.py
alpaca/shell_command.py
alpaca/utils.py
aleya_alpaca-0.1.32.dist-info/LICENSE
aleya_alpaca-0.1.32.dist-info/METADATA
aleya_alpaca-0.1.32.dist-info/WHEEL
aleya_alpaca-0.1.32.dist-info/entry_points.txt
aleya_alpaca-0.1.32.dist-info/top_level.txt
aleya_alpaca-0.1.32.dist-info/RECORD
